src/i2s_clocks.v
module i2s_clocks (
    input wire mclk,                // 22.5792 MHz master clock
    input wire locked,              // Indicates the clocking wizard output is stable

    input wire resetn,              // Active low reset

    output reg sclk,                // Serial clock toggling every 4 mclk periods (2.8224 MHz)
    output wire sclk_pre_rise,      // Pulses for one mclk cycle before rising edge of sclk
    output wire sclk_pre_fall,      // Pulses for one mclk cycle before falling edge of sclk

    output reg lrclk,               // Left-right clock toggling every 32 sclk periods (44.1 kHz)

    output wire rst_n_sync,         // Low when either system is in reset or clocking wizard is not stable

    output wire [4:0] sd_count,     // 0 = MSB, 23 = LSB (24-31 is padding)
    output wire sd_valid            // High when sd_count is between 0 and 23, low during padding
    );

    reg [1:0] mclk_count = 2'b0;    // Counts 4 mclk periods to generate serial clock
    reg [4:0] sclk_count = 5'b0;    // Counts 32 sclk periods to generate lrclk

    // Double flopping to avoid metastability
    reg rst_n_sync_1 = 1'b0;
    reg rst_n_sync_2 = 1'b0;

    wire rst_n_async;
    assign rst_n_async = resetn && locked;
    assign rst_n_sync = rst_n_sync_2;

    // Generate sd_count, it should just be sclk_count delayed by 1 sclk cycle
    assign sd_count = sclk_count - 1'b1;

    // Generate sd_valid
    assign sd_valid = (sd_count >= 5'd0) && (sd_count <= 5'd23);

    assign sclk_pre_rise = (mclk_count == 2'd3) && ~sclk;
    assign sclk_pre_fall = (mclk_count == 2'd3) && sclk;

    always @ (posedge mclk) begin
        rst_n_sync_1 <= rst_n_async;
        rst_n_sync_2 <= rst_n_sync_1;

        if (!rst_n_sync_2) begin
            mclk_count <= 2'b0;
            sclk_count <= 5'b0;
            sclk <= 1'b0;
            lrclk <= 1'b0;
        end else begin
            if (mclk_count < 'd3) begin
                mclk_count <= mclk_count + 1'b1;

            // 4 periods of mclk have passed so invert sclk
            end else begin
                sclk <= ~sclk;
                mclk_count <= 2'b0;

                // Check if 32 sclk periods have occurred for lrclk to be inverted
                if ((sclk_count >= 5'd31) && sclk) begin
                    // Invert lrclk
                    lrclk <= ~lrclk;
                    sclk_count <= 5'b0;
                end else begin
                    sclk_count <= sclk_count + (sclk == 1'b1);  // Increment sclk_count on every falling edge of sclk
                end
            end
        end
    end

endmodule

tb/tb_i2s_clocks.v
`timescale 1ns/1ps

module tb_i2s_clocks;
    reg mclk;               // 22.5792 MHz master clock
    reg locked;             // Indicates the clocking wizard output is stable

    reg resetn;             // Active low reset

    wire sclk;              // Serial clock toggling every 4 mclk periods (2.8224 MHz)
    wire sclk_pre_rise;     // Pulses for one mclk cycle before rising edge of sclk
    wire sclk_pre_fall;     // Pulses for one mclk cycle before falling edge of sclk

    wire lrclk;             // Left-right clock toggling every 32 sclk periods (44.1 kHz)

    wire rst_n_sync;        // Low when either system is in reset or clocking wizard is not stable

    wire [4:0] sd_count;    // 0 = MSB, 23 = LSB (24-31 is padding)
    wire sd_valid;          // High when sd_count is between 0 and 23, low during padding

    i2s_clocks clock_test (
        .mclk(mclk),
        .locked(locked),
        .resetn(resetn),
        .sclk(sclk),
        .sclk_pre_rise(sclk_pre_rise), .sclk_pre_fall(sclk_pre_fall),
        .lrclk(lrclk),
        .rst_n_sync(rst_n_sync),
        .sd_count(sd_count), .sd_valid(sd_valid)
    );

    always begin
        #22.144 mclk = ~mclk;
    end

    initial begin
        $dumpfile("tb_i2s_clocks.vcd");
        $dumpvars(0, tb_i2s_clocks);

        resetn = 0;
        locked = 0;
        mclk = 0;

        #50;
        resetn = 1;

        #20; locked = 1;

        #100000
        $finish;
    end

endmodule

tb/vaporview/tb_i2s_clocks.vcd
$date
	Thu Oct  8 12:20:17 2026
$end
$version
	Icarus Verilog
$end
$timescale
	1ps
$end
$scope module tb_i2s_clocks $end
$var wire 1 ! sd_valid $end
$var wire 5 " sd_count [4:0] $end
$var wire 1 # sclk_pre_rise $end
$var wire 1 $ sclk_pre_fall $end
$var wire 1 % sclk $end
$var wire 1 & rst_n_sync $end
$var wire 1 ' lrclk $end
$var reg 1 ( locked $end
$var reg 1 ) mclk $end
$var reg 1 * resetn $end
$scope module clock_test $end
$var wire 1 ( locked $end
$var wire 1 ) mclk $end
$var wire 1 * resetn $end
$var wire 1 + rst_n_async $end
$var wire 1 & rst_n_sync $end
$var wire 1 $ sclk_pre_fall $end
$var wire 1 # sclk_pre_rise $end
$var wire 1 ! sd_valid $end
$var wire 5 , sd_count [4:0] $end
$var reg 1 ' lrclk $end
$var reg 2 - mclk_count [1:0] $end
$var reg 1 . rst_n_sync_1 $end
$var reg 1 / rst_n_sync_2 $end
$var reg 1 % sclk $end
$var reg 5 0 sclk_count [4:0] $end
$upscope $end
$upscope $end
$enddefinitions $end
$comment Show the parameter values. $end
$dumpall
$end
#0
$dumpvars
b0 0
0/
0.
b0 -
b11111 ,
0+
0*
0)
0(
x'
0&
x%
0$
0#
b11111 "
0!
$end
#22144
0'
0%
1)
#44288
0)
#50000
1*
#66432
1)
#70000
1+
1(
#88576
0)
#110720
1.
1)
#132864
0)
#155008
1&
1/
1)
#177152
0)
#199296
b1 -
1)
#221440
0)
#243584
b10 -
1)
#265728
0)
#287872
1#
b11 -
1)
#310016
0)
#332160
0#
b0 -
1%
1)
#354304
0)
#376448
b1 -
1)
#398592
0)
#420736
b10 -
1)
#442880
0)
#465024
1$
b11 -
1)
#487168
0)
#509312
1!
0$
b0 "
b0 ,
b1 0
b0 -
0%
1)
#531456
0)
#553600
b1 -
1)
#575744
0)
#597888
b10 -
1)
#620032
0)
#642176
1#
b11 -
1)
#664320
0)
#686464
0#
b0 -
1%
1)
#708608
0)
#730752
b1 -
1)
#752896
0)
#775040
b10 -
1)
#797184
0)
#819328
1$
b11 -
1)
#841472
0)
#863616
0$
b1 "
b1 ,
b10 0
b0 -
0%
1)
#885760
0)
#907904
b1 -
1)
#930048
0)
#952192
b10 -
1)
#974336
0)
#996480
1#
b11 -
1)
#1018624
0)
#1040768
0#
b0 -
1%
1)
#1062912
0)
#1085056
b1 -
1)
#1107200
0)
#1129344
b10 -
1)
#1151488
0)
#1173632
1$
b11 -
1)
#1195776
0)
#1217920
0$
b10 "
b10 ,
b11 0
b0 -
0%
1)
#1240064
0)
#1262208
b1 -
1)
#1284352
0)
#1306496
b10 -
1)
#1328640
0)
#1350784
1#
b11 -
1)
#1372928
0)
#1395072
0#
b0 -
1%
1)
#1417216
0)
#1439360
b1 -
1)
#1461504
0)
#1483648
b10 -
1)
#1505792
0)
#1527936
1$
b11 -
1)
#1550080
0)
#1572224
0$
b11 "
b11 ,
b100 0
b0 -
0%
1)
#1594368
0)
#1616512
b1 -
1)
#1638656
0)
#1660800
b10 -
1)
#1682944
0)
#1705088
1#
b11 -
1)
#1727232
0)
#1749376
0#
b0 -
1%
1)
#1771520
0)
#1793664
b1 -
1)
#1815808
0)
#1837952
b10 -
1)
#1860096
0)
#1882240
1$
b11 -
1)
#1904384
0)
#1926528
0$
b100 "
b100 ,
b101 0
b0 -
0%
1)
#1948672
0)
#1970816
b1 -
1)
#1992960
0)
#2015104
b10 -
1)
#2037248
0)
#2059392
1#
b11 -
1)
#2081536
0)
#2103680
0#
b0 -
1%
1)
#2125824
0)
#2147968
b1 -
1)
#2170112
0)
#2192256
b10 -
1)
#2214400
0)
#2236544
1$
b11 -
1)
#2258688
0)
#2280832
0$
b101 "
b101 ,
b110 0
b0 -
0%
1)
#2302976
0)
#2325120
b1 -
1)
#2347264
0)
#2369408
b10 -
1)
#2391552
0)
#2413696
1#
b11 -
1)
#2435840
0)
#2457984
0#
b0 -
1%
1)
#2480128
0)
#2502272
b1 -
1)
#2524416
0)
#2546560
b10 -
1)
#2568704
0)
#2590848
1$
b11 -
1)
#2612992
0)
#2635136
0$
b110 "
b110 ,
b111 0
b0 -
0%
1)
#2657280
0)
#2679424
b1 -
1)
#2701568
0)
#2723712
b10 -
1)
#2745856
0)
#2768000
1#
b11 -
1)
#2790144
0)
#2812288
0#
b0 -
1%
1)
#2834432
0)
#2856576
b1 -
1)
#2878720
0)
#2900864
b10 -
1)
#2923008
0)
#2945152
1$
b11 -
1)
#2967296
0)
#2989440
0$
b111 "
b111 ,
b1000 0
b0 -
0%
1)
#3011584
0)
#3033728
b1 -
1)
#3055872
0)
#3078016
b10 -
1)
#3100160
0)
#3122304
1#
b11 -
1)
#3144448
0)
#3166592
0#
b0 -
1%
1)
#3188736
0)
#3210880
b1 -
1)
#3233024
0)
#3255168
b10 -
1)
#3277312
0)
#3299456
1$
b11 -
1)
#3321600
0)
#3343744
0$
b1000 "
b1000 ,
b1001 0
b0 -
0%
1)
#3365888
0)
#3388032
b1 -
1)
#3410176
0)
#3432320
b10 -
1)
#3454464
0)
#3476608
1#
b11 -
1)
#3498752
0)
#3520896
0#
b0 -
1%
1)
#3543040
0)
#3565184
b1 -
1)
#3587328
0)
#3609472
b10 -
1)
#3631616
0)
#3653760
1$
b11 -
1)
#3675904
0)
#3698048
0$
b1001 "
b1001 ,
b1010 0
b0 -
0%
1)
#3720192
0)
#3742336
b1 -
1)
#3764480
0)
#3786624
b10 -
1)
#3808768
0)
#3830912
1#
b11 -
1)
#3853056
0)
#3875200
0#
b0 -
1%
1)
#3897344
0)
#3919488
b1 -
1)
#3941632
0)
#3963776
b10 -
1)
#3985920
0)
#4008064
1$
b11 -
1)
#4030208
0)
#4052352
0$
b1010 "
b1010 ,
b1011 0
b0 -
0%
1)
#4074496
0)
#4096640
b1 -
1)
#4118784
0)
#4140928
b10 -
1)
#4163072
0)
#4185216
1#
b11 -
1)
#4207360
0)
#4229504
0#
b0 -
1%
1)
#4251648
0)
#4273792
b1 -
1)
#4295936
0)
#4318080
b10 -
1)
#4340224
0)
#4362368
1$
b11 -
1)
#4384512
0)
#4406656
0$
b1011 "
b1011 ,
b1100 0
b0 -
0%
1)
#4428800
0)
#4450944
b1 -
1)
#4473088
0)
#4495232
b10 -
1)
#4517376
0)
#4539520
1#
b11 -
1)
#4561664
0)
#4583808
0#
b0 -
1%
1)
#4605952
0)
#4628096
b1 -
1)
#4650240
0)
#4672384
b10 -
1)
#4694528
0)
#4716672
1$
b11 -
1)
#4738816
0)
#4760960
0$
b1100 "
b1100 ,
b1101 0
b0 -
0%
1)
#4783104
0)
#4805248
b1 -
1)
#4827392
0)
#4849536
b10 -
1)
#4871680
0)
#4893824
1#
b11 -
1)
#4915968
0)
#4938112
0#
b0 -
1%
1)
#4960256
0)
#4982400
b1 -
1)
#5004544
0)
#5026688
b10 -
1)
#5048832
0)
#5070976
1$
b11 -
1)
#5093120
0)
#5115264
0$
b1101 "
b1101 ,
b1110 0
b0 -
0%
1)
#5137408
0)
#5159552
b1 -
1)
#5181696
0)
#5203840
b10 -
1)
#5225984
0)
#5248128
1#
b11 -
1)
#5270272
0)
#5292416
0#
b0 -
1%
1)
#5314560
0)
#5336704
b1 -
1)
#5358848
0)
#5380992
b10 -
1)
#5403136
0)
#5425280
1$
b11 -
1)
#5447424
0)
#5469568
0$
b1110 "
b1110 ,
b1111 0
b0 -
0%
1)
#5491712
0)
#5513856
b1 -
1)
#5536000
0)
#5558144
b10 -
1)
#5580288
0)
#5602432
1#
b11 -
1)
#5624576
0)
#5646720
0#
b0 -
1%
1)
#5668864
0)
#5691008
b1 -
1)
#5713152
0)
#5735296
b10 -
1)
#5757440
0)
#5779584
1$
b11 -
1)
#5801728
0)
#5823872
0$
b1111 "
b1111 ,
b10000 0
b0 -
0%
1)
#5846016
0)
#5868160
b1 -
1)
#5890304
0)
#5912448
b10 -
1)
#5934592
0)
#5956736
1#
b11 -
1)
#5978880
0)
#6001024
0#
b0 -
1%
1)
#6023168
0)
#6045312
b1 -
1)
#6067456
0)
#6089600
b10 -
1)
#6111744
0)
#6133888
1$
b11 -
1)
#6156032
0)
#6178176
0$
b10000 "
b10000 ,
b10001 0
b0 -
0%
1)
#6200320
0)
#6222464
b1 -
1)
#6244608
0)
#6266752
b10 -
1)
#6288896
0)
#6311040
1#
b11 -
1)
#6333184
0)
#6355328
0#
b0 -
1%
1)
#6377472
0)
#6399616
b1 -
1)
#6421760
0)
#6443904
b10 -
1)
#6466048
0)
#6488192
1$
b11 -
1)
#6510336
0)
#6532480
0$
b10001 "
b10001 ,
b10010 0
b0 -
0%
1)
#6554624
0)
#6576768
b1 -
1)
#6598912
0)
#6621056
b10 -
1)
#6643200
0)
#6665344
1#
b11 -
1)
#6687488
0)
#6709632
0#
b0 -
1%
1)
#6731776
0)
#6753920
b1 -
1)
#6776064
0)
#6798208
b10 -
1)
#6820352
0)
#6842496
1$
b11 -
1)
#6864640
0)
#6886784
0$
b10010 "
b10010 ,
b10011 0
b0 -
0%
1)
#6908928
0)
#6931072
b1 -
1)
#6953216
0)
#6975360
b10 -
1)
#6997504
0)
#7019648
1#
b11 -
1)
#7041792
0)
#7063936
0#
b0 -
1%
1)
#7086080
0)
#7108224
b1 -
1)
#7130368
0)
#7152512
b10 -
1)
#7174656
0)
#7196800
1$
b11 -
1)
#7218944
0)
#7241088
0$
b10011 "
b10011 ,
b10100 0
b0 -
0%
1)
#7263232
0)
#7285376
b1 -
1)
#7307520
0)
#7329664
b10 -
1)
#7351808
0)
#7373952
1#
b11 -
1)
#7396096
0)
#7418240
0#
b0 -
1%
1)
#7440384
0)
#7462528
b1 -
1)
#7484672
0)
#7506816
b10 -
1)
#7528960
0)
#7551104
1$
b11 -
1)
#7573248
0)
#7595392
0$
b10100 "
b10100 ,
b10101 0
b0 -
0%
1)
#7617536
0)
#7639680
b1 -
1)
#7661824
0)
#7683968
b10 -
1)
#7706112
0)
#7728256
1#
b11 -
1)
#7750400
0)
#7772544
0#
b0 -
1%
1)
#7794688
0)
#7816832
b1 -
1)
#7838976
0)
#7861120
b10 -
1)
#7883264
0)
#7905408
1$
b11 -
1)
#7927552
0)
#7949696
0$
b10101 "
b10101 ,
b10110 0
b0 -
0%
1)
#7971840
0)
#7993984
b1 -
1)
#8016128
0)
#8038272
b10 -
1)
#8060416
0)
#8082560
1#
b11 -
1)
#8104704
0)
#8126848
0#
b0 -
1%
1)
#8148992
0)
#8171136
b1 -
1)
#8193280
0)
#8215424
b10 -
1)
#8237568
0)
#8259712
1$
b11 -
1)
#8281856
0)
#8304000
0$
b10110 "
b10110 ,
b10111 0
b0 -
0%
1)
#8326144
0)
#8348288
b1 -
1)
#8370432
0)
#8392576
b10 -
1)
#8414720
0)
#8436864
1#
b11 -
1)
#8459008
0)
#8481152
0#
b0 -
1%
1)
#8503296
0)
#8525440
b1 -
1)
#8547584
0)
#8569728
b10 -
1)
#8591872
0)
#8614016
1$
b11 -
1)
#8636160
0)
#8658304
0$
b10111 "
b10111 ,
b11000 0
b0 -
0%
1)
#8680448
0)
#8702592
b1 -
1)
#8724736
0)
#8746880
b10 -
1)
#8769024
0)
#8791168
1#
b11 -
1)
#8813312
0)
#8835456
0#
b0 -
1%
1)
#8857600
0)
#8879744
b1 -
1)
#8901888
0)
#8924032
b10 -
1)
#8946176
0)
#8968320
1$
b11 -
1)
#8990464
0)
#9012608
0!
0$
b11000 "
b11000 ,
b11001 0
b0 -
0%
1)
#9034752
0)
#9056896
b1 -
1)
#9079040
0)
#9101184
b10 -
1)
#9123328
0)
#9145472
1#
b11 -
1)
#9167616
0)
#9189760
0#
b0 -
1%
1)
#9211904
0)
#9234048
b1 -
1)
#9256192
0)
#9278336
b10 -
1)
#9300480
0)
#9322624
1$
b11 -
1)
#9344768
0)
#9366912
0$
b11001 "
b11001 ,
b11010 0
b0 -
0%
1)
#9389056
0)
#9411200
b1 -
1)
#9433344
0)
#9455488
b10 -
1)
#9477632
0)
#9499776
1#
b11 -
1)
#9521920
0)
#9544064
0#
b0 -
1%
1)
#9566208
0)
#9588352
b1 -
1)
#9610496
0)
#9632640
b10 -
1)
#9654784
0)
#9676928
1$
b11 -
1)
#9699072
0)
#9721216
0$
b11010 "
b11010 ,
b11011 0
b0 -
0%
1)
#9743360
0)
#9765504
b1 -
1)
#9787648
0)
#9809792
b10 -
1)
#9831936
0)
#9854080
1#
b11 -
1)
#9876224
0)
#9898368
0#
b0 -
1%
1)
#9920512
0)
#9942656
b1 -
1)
#9964800
0)
#9986944
b10 -
1)
#10009088
0)
#10031232
1$
b11 -
1)
#10053376
0)
#10075520
0$
b11011 "
b11011 ,
b11100 0
b0 -
0%
1)
#10097664
0)
#10119808
b1 -
1)
#10141952
0)
#10164096
b10 -
1)
#10186240
0)
#10208384
1#
b11 -
1)
#10230528
0)
#10252672
0#
b0 -
1%
1)
#10274816
0)
#10296960
b1 -
1)
#10319104
0)
#10341248
b10 -
1)
#10363392
0)
#10385536
1$
b11 -
1)
#10407680
0)
#10429824
0$
b11100 "
b11100 ,
b11101 0
b0 -
0%
1)
#10451968
0)
#10474112
b1 -
1)
#10496256
0)
#10518400
b10 -
1)
#10540544
0)
#10562688
1#
b11 -
1)
#10584832
0)
#10606976
0#
b0 -
1%
1)
#10629120
0)
#10651264
b1 -
1)
#10673408
0)
#10695552
b10 -
1)
#10717696
0)
#10739840
1$
b11 -
1)
#10761984
0)
#10784128
0$
b11101 "
b11101 ,
b11110 0
b0 -
0%
1)
#10806272
0)
#10828416
b1 -
1)
#10850560
0)
#10872704
b10 -
1)
#10894848
0)
#10916992
1#
b11 -
1)
#10939136
0)
#10961280
0#
b0 -
1%
1)
#10983424
0)
#11005568
b1 -
1)
#11027712
0)
#11049856
b10 -
1)
#11072000
0)
#11094144
1$
b11 -
1)
#11116288
0)
#11138432
0$
b11110 "
b11110 ,
b11111 0
b0 -
0%
1)
#11160576
0)
#11182720
b1 -
1)
#11204864
0)
#11227008
b10 -
1)
#11249152
0)
#11271296
1#
b11 -
1)
#11293440
0)
#11315584
0#
b0 -
1%
1)
#11337728
0)
#11359872
b1 -
1)
#11382016
0)
#11404160
b10 -
1)
#11426304
0)
#11448448
1$
b11 -
1)
#11470592
0)
#11492736
0$
b11111 "
b11111 ,
b0 0
1'
b0 -
0%
1)
#11514880
0)
#11537024
b1 -
1)
#11559168
0)
#11581312
b10 -
1)
#11603456
0)
#11625600
1#
b11 -
1)
#11647744
0)
#11669888
0#
b0 -
1%
1)
#11692032
0)
#11714176
b1 -
1)
#11736320
0)
#11758464
b10 -
1)
#11780608
0)
#11802752
1$
b11 -
1)
#11824896
0)
#11847040
1!
0$
b0 "
b0 ,
b1 0
b0 -
0%
1)
#11869184
0)
#11891328
b1 -
1)
#11913472
0)
#11935616
b10 -
1)
#11957760
0)
#11979904
1#
b11 -
1)
#12002048
0)
#12024192
0#
b0 -
1%
1)
#12046336
0)
#12068480
b1 -
1)
#12090624
0)
#12112768
b10 -
1)
#12134912
0)
#12157056
1$
b11 -
1)
#12179200
0)
#12201344
0$
b1 "
b1 ,
b10 0
b0 -
0%
1)
#12223488
0)
#12245632
b1 -
1)
#12267776
0)
#12289920
b10 -
1)
#12312064
0)
#12334208
1#
b11 -
1)
#12356352
0)
#12378496
0#
b0 -
1%
1)
#12400640
0)
#12422784
b1 -
1)
#12444928
0)
#12467072
b10 -
1)
#12489216
0)
#12511360
1$
b11 -
1)
#12533504
0)
#12555648
0$
b10 "
b10 ,
b11 0
b0 -
0%
1)
#12577792
0)
#12599936
b1 -
1)
#12622080
0)
#12644224
b10 -
1)
#12666368
0)
#12688512
1#
b11 -
1)
#12710656
0)
#12732800
0#
b0 -
1%
1)
#12754944
0)
#12777088
b1 -
1)
#12799232
0)
#12821376
b10 -
1)
#12843520
0)
#12865664
1$
b11 -
1)
#12887808
0)
#12909952
0$
b11 "
b11 ,
b100 0
b0 -
0%
1)
#12932096
0)
#12954240
b1 -
1)
#12976384
0)
#12998528
b10 -
1)
#13020672
0)
#13042816
1#
b11 -
1)
#13064960
0)
#13087104
0#
b0 -
1%
1)
#13109248
0)
#13131392
b1 -
1)
#13153536
0)
#13175680
b10 -
1)
#13197824
0)
#13219968
1$
b11 -
1)
#13242112
0)
#13264256
0$
b100 "
b100 ,
b101 0
b0 -
0%
1)
#13286400
0)
#13308544
b1 -
1)
#13330688
0)
#13352832
b10 -
1)
#13374976
0)
#13397120
1#
b11 -
1)
#13419264
0)
#13441408
0#
b0 -
1%
1)
#13463552
0)
#13485696
b1 -
1)
#13507840
0)
#13529984
b10 -
1)
#13552128
0)
#13574272
1$
b11 -
1)
#13596416
0)
#13618560
0$
b101 "
b101 ,
b110 0
b0 -
0%
1)
#13640704
0)
#13662848
b1 -
1)
#13684992
0)
#13707136
b10 -
1)
#13729280
0)
#13751424
1#
b11 -
1)
#13773568
0)
#13795712
0#
b0 -
1%
1)
#13817856
0)
#13840000
b1 -
1)
#13862144
0)
#13884288
b10 -
1)
#13906432
0)
#13928576
1$
b11 -
1)
#13950720
0)
#13972864
0$
b110 "
b110 ,
b111 0
b0 -
0%
1)
#13995008
0)
#14017152
b1 -
1)
#14039296
0)
#14061440
b10 -
1)
#14083584
0)
#14105728
1#
b11 -
1)
#14127872
0)
#14150016
0#
b0 -
1%
1)
#14172160
0)
#14194304
b1 -
1)
#14216448
0)
#14238592
b10 -
1)
#14260736
0)
#14282880
1$
b11 -
1)
#14305024
0)
#14327168
0$
b111 "
b111 ,
b1000 0
b0 -
0%
1)
#14349312
0)
#14371456
b1 -
1)
#14393600
0)
#14415744
b10 -
1)
#14437888
0)
#14460032
1#
b11 -
1)
#14482176
0)
#14504320
0#
b0 -
1%
1)
#14526464
0)
#14548608
b1 -
1)
#14570752
0)
#14592896
b10 -
1)
#14615040
0)
#14637184
1$
b11 -
1)
#14659328
0)
#14681472
0$
b1000 "
b1000 ,
b1001 0
b0 -
0%
1)
#14703616
0)
#14725760
b1 -
1)
#14747904
0)
#14770048
b10 -
1)
#14792192
0)
#14814336
1#
b11 -
1)
#14836480
0)
#14858624
0#
b0 -
1%
1)
#14880768
0)
#14902912
b1 -
1)
#14925056
0)
#14947200
b10 -
1)
#14969344
0)
#14991488
1$
b11 -
1)
#15013632
0)
#15035776
0$
b1001 "
b1001 ,
b1010 0
b0 -
0%
1)
#15057920
0)
#15080064
b1 -
1)
#15102208
0)
#15124352
b10 -
1)
#15146496
0)
#15168640
1#
b11 -
1)
#15190784
0)
#15212928
0#
b0 -
1%
1)
#15235072
0)
#15257216
b1 -
1)
#15279360
0)
#15301504
b10 -
1)
#15323648
0)
#15345792
1$
b11 -
1)
#15367936
0)
#15390080
0$
b1010 "
b1010 ,
b1011 0
b0 -
0%
1)
#15412224
0)
#15434368
b1 -
1)
#15456512
0)
#15478656
b10 -
1)
#15500800
0)
#15522944
1#
b11 -
1)
#15545088
0)
#15567232
0#
b0 -
1%
1)
#15589376
0)
#15611520
b1 -
1)
#15633664
0)
#15655808
b10 -
1)
#15677952
0)
#15700096
1$
b11 -
1)
#15722240
0)
#15744384
0$
b1011 "
b1011 ,
b1100 0
b0 -
0%
1)
#15766528
0)
#15788672
b1 -
1)
#15810816
0)
#15832960
b10 -
1)
#15855104
0)
#15877248
1#
b11 -
1)
#15899392
0)
#15921536
0#
b0 -
1%
1)
#15943680
0)
#15965824
b1 -
1)
#15987968
0)
#16010112
b10 -
1)
#16032256
0)
#16054400
1$
b11 -
1)
#16076544
0)
#16098688
0$
b1100 "
b1100 ,
b1101 0
b0 -
0%
1)
#16120832
0)
#16142976
b1 -
1)
#16165120
0)
#16187264
b10 -
1)
#16209408
0)
#16231552
1#
b11 -
1)
#16253696
0)
#16275840
0#
b0 -
1%
1)
#16297984
0)
#16320128
b1 -
1)
#16342272
0)
#16364416
b10 -
1)
#16386560
0)
#16408704
1$
b11 -
1)
#16430848
0)
#16452992
0$
b1101 "
b1101 ,
b1110 0
b0 -
0%
1)
#16475136
0)
#16497280
b1 -
1)
#16519424
0)
#16541568
b10 -
1)
#16563712
0)
#16585856
1#
b11 -
1)
#16608000
0)
#16630144
0#
b0 -
1%
1)
#16652288
0)
#16674432
b1 -
1)
#16696576
0)
#16718720
b10 -
1)
#16740864
0)
#16763008
1$
b11 -
1)
#16785152
0)
#16807296
0$
b1110 "
b1110 ,
b1111 0
b0 -
0%
1)
#16829440
0)
#16851584
b1 -
1)
#16873728
0)
#16895872
b10 -
1)
#16918016
0)
#16940160
1#
b11 -
1)
#16962304
0)
#16984448
0#
b0 -
1%
1)
#17006592
0)
#17028736
b1 -
1)
#17050880
0)
#17073024
b10 -
1)
#17095168
0)
#17117312
1$
b11 -
1)
#17139456
0)
#17161600
0$
b1111 "
b1111 ,
b10000 0
b0 -
0%
1)
#17183744
0)
#17205888
b1 -
1)
#17228032
0)
#17250176
b10 -
1)
#17272320
0)
#17294464
1#
b11 -
1)
#17316608
0)
#17338752
0#
b0 -
1%
1)
#17360896
0)
#17383040
b1 -
1)
#17405184
0)
#17427328
b10 -
1)
#17449472
0)
#17471616
1$
b11 -
1)
#17493760
0)
#17515904
0$
b10000 "
b10000 ,
b10001 0
b0 -
0%
1)
#17538048
0)
#17560192
b1 -
1)
#17582336
0)
#17604480
b10 -
1)
#17626624
0)
#17648768
1#
b11 -
1)
#17670912
0)
#17693056
0#
b0 -
1%
1)
#17715200
0)
#17737344
b1 -
1)
#17759488
0)
#17781632
b10 -
1)
#17803776
0)
#17825920
1$
b11 -
1)
#17848064
0)
#17870208
0$
b10001 "
b10001 ,
b10010 0
b0 -
0%
1)
#17892352
0)
#17914496
b1 -
1)
#17936640
0)
#17958784
b10 -
1)
#17980928
0)
#18003072
1#
b11 -
1)
#18025216
0)
#18047360
0#
b0 -
1%
1)
#18069504
0)
#18091648
b1 -
1)
#18113792
0)
#18135936
b10 -
1)
#18158080
0)
#18180224
1$
b11 -
1)
#18202368
0)
#18224512
0$
b10010 "
b10010 ,
b10011 0
b0 -
0%
1)
#18246656
0)
#18268800
b1 -
1)
#18290944
0)
#18313088
b10 -
1)
#18335232
0)
#18357376
1#
b11 -
1)
#18379520
0)
#18401664
0#
b0 -
1%
1)
#18423808
0)
#18445952
b1 -
1)
#18468096
0)
#18490240
b10 -
1)
#18512384
0)
#18534528
1$
b11 -
1)
#18556672
0)
#18578816
0$
b10011 "
b10011 ,
b10100 0
b0 -
0%
1)
#18600960
0)
#18623104
b1 -
1)
#18645248
0)
#18667392
b10 -
1)
#18689536
0)
#18711680
1#
b11 -
1)
#18733824
0)
#18755968
0#
b0 -
1%
1)
#18778112
0)
#18800256
b1 -
1)
#18822400
0)
#18844544
b10 -
1)
#18866688
0)
#18888832
1$
b11 -
1)
#18910976
0)
#18933120
0$
b10100 "
b10100 ,
b10101 0
b0 -
0%
1)
#18955264
0)
#18977408
b1 -
1)
#18999552
0)
#19021696
b10 -
1)
#19043840
0)
#19065984
1#
b11 -
1)
#19088128
0)
#19110272
0#
b0 -
1%
1)
#19132416
0)
#19154560
b1 -
1)
#19176704
0)
#19198848
b10 -
1)
#19220992
0)
#19243136
1$
b11 -
1)
#19265280
0)
#19287424
0$
b10101 "
b10101 ,
b10110 0
b0 -
0%
1)
#19309568
0)
#19331712
b1 -
1)
#19353856
0)
#19376000
b10 -
1)
#19398144
0)
#19420288
1#
b11 -
1)
#19442432
0)
#19464576
0#
b0 -
1%
1)
#19486720
0)
#19508864
b1 -
1)
#19531008
0)
#19553152
b10 -
1)
#19575296
0)
#19597440
1$
b11 -
1)
#19619584
0)
#19641728
0$
b10110 "
b10110 ,
b10111 0
b0 -
0%
1)
#19663872
0)
#19686016
b1 -
1)
#19708160
0)
#19730304
b10 -
1)
#19752448
0)
#19774592
1#
b11 -
1)
#19796736
0)
#19818880
0#
b0 -
1%
1)
#19841024
0)
#19863168
b1 -
1)
#19885312
0)
#19907456
b10 -
1)
#19929600
0)
#19951744
1$
b11 -
1)
#19973888
0)
#19996032
0$
b10111 "
b10111 ,
b11000 0
b0 -
0%
1)
#20018176
0)
#20040320
b1 -
1)
#20062464
0)
#20084608
b10 -
1)
#20106752
0)
#20128896
1#
b11 -
1)
#20151040
0)
#20173184
0#
b0 -
1%
1)
#20195328
0)
#20217472
b1 -
1)
#20239616
0)
#20261760
b10 -
1)
#20283904
0)
#20306048
1$
b11 -
1)
#20328192
0)
#20350336
0!
0$
b11000 "
b11000 ,
b11001 0
b0 -
0%
1)
#20372480
0)
#20394624
b1 -
1)
#20416768
0)
#20438912
b10 -
1)
#20461056
0)
#20483200
1#
b11 -
1)
#20505344
0)
#20527488
0#
b0 -
1%
1)
#20549632
0)
#20571776
b1 -
1)
#20593920
0)
#20616064
b10 -
1)
#20638208
0)
#20660352
1$
b11 -
1)
#20682496
0)
#20704640
0$
b11001 "
b11001 ,
b11010 0
b0 -
0%
1)
#20726784
0)
#20748928
b1 -
1)
#20771072
0)
#20793216
b10 -
1)
#20815360
0)
#20837504
1#
b11 -
1)
#20859648
0)
#20881792
0#
b0 -
1%
1)
#20903936
0)
#20926080
b1 -
1)
#20948224
0)
#20970368
b10 -
1)
#20992512
0)
#21014656
1$
b11 -
1)
#21036800
0)
#21058944
0$
b11010 "
b11010 ,
b11011 0
b0 -
0%
1)
#21081088
0)
#21103232
b1 -
1)
#21125376
0)
#21147520
b10 -
1)
#21169664
0)
#21191808
1#
b11 -
1)
#21213952
0)
#21236096
0#
b0 -
1%
1)
#21258240
0)
#21280384
b1 -
1)
#21302528
0)
#21324672
b10 -
1)
#21346816
0)
#21368960
1$
b11 -
1)
#21391104
0)
#21413248
0$
b11011 "
b11011 ,
b11100 0
b0 -
0%
1)
#21435392
0)
#21457536
b1 -
1)
#21479680
0)
#21501824
b10 -
1)
#21523968
0)
#21546112
1#
b11 -
1)
#21568256
0)
#21590400
0#
b0 -
1%
1)
#21612544
0)
#21634688
b1 -
1)
#21656832
0)
#21678976
b10 -
1)
#21701120
0)
#21723264
1$
b11 -
1)
#21745408
0)
#21767552
0$
b11100 "
b11100 ,
b11101 0
b0 -
0%
1)
#21789696
0)
#21811840
b1 -
1)
#21833984
0)
#21856128
b10 -
1)
