src/line_out.v
module line_out (
    input wire mclk,                // 22.5792 MHz master clock
    input wire sclk_pre_fall,       // Pulses for one mclk cycle before falling edge of sclk
    input wire lrclk,               // Left-right clock, 1 = right, 0 = left

    input wire rst_n_sync,          // Low when either system is in reset or clocking wizard is not stable

    input wire [23:0] left_data,    // 24-bit data on the left channel
    input wire [23:0] right_data,   // 24-bit data on the right channel

    input wire [4:0] sd_count,      // 0 = MSB, 23 = LSB (24-31 is padding)

    output reg sd_dac               // Serial data to DAC
    );

    always @ (posedge mclk) begin
        if (!rst_n_sync) begin
            sd_dac <= 1'b0;
        end else begin
            if (sclk_pre_fall) begin
                if (sd_count == 5'd31) begin
                    if (lrclk)
                        sd_dac <= right_data[23];
                    else
                        sd_dac <= left_data[23];
                end else if ((sd_count >= 5'b0) && (sd_count <= 5'd22)) begin
                    if (lrclk)
                        sd_dac <= right_data[5'd22 - sd_count];
                    else
                        sd_dac <= left_data[5'd22 - sd_count];
                end else begin
                    // When receiving padding, put 0s on dac
                    sd_dac <= 1'b0;
                end
            end
        end
    end

endmodule

src/i2s_clocks.v
module i2s_clocks (
    input wire mclk,                // 22.5792 MHz master clock
    input wire locked,              // Indicates the clocking wizard output is stable

    input wire resetn,              // Active low reset

    output reg sclk,                // Serial clock toggling every 4 mclk periods (2.8224 MHz)
    output wire sclk_pre_rise,      // Pulses for one mclk cycle before rising edge of sclk
    output wire sclk_pre_fall,      // Pulses for one mclk cycle before falling edge of sclk

    output reg lrclk,               // Left-right clock toggling every 32 sclk periods (44.1 kHz)

    output wire rst_n_sync,         // Low when either system is in reset or clocking wizard is not stable

    output wire [4:0] sd_count,     // 0 = MSB, 23 = LSB (24-31 is padding)
    output wire sd_valid            // High when sd_count is between 0 and 23, low during padding
    );

    reg [1:0] mclk_count = 2'b0;    // Counts 4 mclk periods to generate serial clock
    reg [4:0] sclk_count = 5'b0;    // Counts 32 sclk periods to generate lrclk

    // Double flopping to avoid metastability
    reg rst_n_sync_1 = 1'b0;
    reg rst_n_sync_2 = 1'b0;

    wire rst_n_async;
    assign rst_n_async = resetn && locked;
    assign rst_n_sync = rst_n_sync_2;

    // Generate sd_count, it should just be sclk_count delayed by 1 sclk cycle
    assign sd_count = sclk_count - 1'b1;

    // Generate sd_valid
    assign sd_valid = (sd_count >= 5'd0) && (sd_count <= 5'd23);

    assign sclk_pre_rise = (mclk_count == 2'd3) && ~sclk;
    assign sclk_pre_fall = (mclk_count == 2'd3) && sclk;

    always @ (posedge mclk) begin
        rst_n_sync_1 <= rst_n_async;
        rst_n_sync_2 <= rst_n_sync_1;

        if (!rst_n_sync_2) begin
            mclk_count <= 2'b0;
            sclk_count <= 5'b0;
            sclk <= 1'b0;
            lrclk <= 1'b0;
        end else begin
            if (mclk_count < 'd3) begin
                mclk_count <= mclk_count + 1'b1;

            // 4 periods of mclk have passed so invert sclk
            end else begin
                sclk <= ~sclk;
                mclk_count <= 2'b0;

                // Check if 32 sclk periods have occurred for lrclk to be inverted
                if ((sclk_count >= 5'd31) && sclk) begin
                    // Invert lrclk
                    lrclk <= ~lrclk;
                    sclk_count <= 5'b0;
                end else begin
                    sclk_count <= sclk_count + (sclk == 1'b1);  // Increment sclk_count on every falling edge of sclk
                end
            end
        end
    end

endmodule

tb/tb_line_out.v
`timescale 1ns/1ps

module tb_line_out;
    reg mclk;               // 22.5792 MHz master clock
    reg sclk_pre_fall;      // Pulses for one mclk cycle before rising edge of sclk
    reg lrclk;              // Left-right clock, 1 = right, 0 = left

    reg rst_n_sync;         // Low when either system is in reset or clocking wizard is not stable

    reg [23:0] left_data;   // 24-bit data on the left channel
    reg [23:0] right_data;  // 24-bit data on the right channel
    reg [4:0] sd_count;     // 0 = MSB, 23 = LSB

    wire sd_dac;

    reg locked;
    reg resetn;
    reg sclk;

    i2s_clocks clock_test (
        .mclk(mclk),
        .locked(locked),
        .resetn(resetn),
        .sclk(sclk),
        .sclk_pre_rise(), .sclk_pre_fall(sclk_pre_fall),
        .lrclk(lrclk),
        .rst_n_sync(rst_n_sync),
        .sd_count(sd_count), .sd_valid()
    );

    line_out output_test (
        .mclk(mclk),
        .sclk_pre_fall(sclk_pre_fall),
        .lrclk(lrclk),
        .rst_n_sync(rst_n_sync),
        .left_data(left_data), .right_data(right_data),
        .sd_count(sd_count),
        .sd_dac(sd_dac)
    );

    always begin
        #10 mclk = ~mclk; // Just going to assume mclk has 20ns period instead of 44.289ns
        // This means serial clock toggles every 80ns and lrclk toggles every 10240ns
    end

    initial begin
        $dumpfile("tb_line_out.vcd");
        $dumpvars(0, tb_line_out);

        resetn = 0;
        locked = 0;
        mclk = 0;

        #50;
        resetn = 1;

        #20; locked = 1;

        @ (posedge lrclk);
        receive_data(24'hDADBAD, 1);
        receive_data(24'h1A2B3C, 0);
        #1000;

        $finish;
    end

    task receive_data(input [23:0] data, input channel); // Channel = 1 means right, channel = 0 means left
        integer i;
        begin
            wait (sd_count == 23);
            @ (posedge sclk);
            if (channel) right_data = data;
            else
                left_data = data;
        end
    endtask

endmodule

tb/vaporview/tb_line_out.vcd
$date
	Thu Oct  8 08:55:13 2026
$end
$version
	Icarus Verilog
$end
$timescale
	1ps
$end
$scope module tb_line_out $end
$var wire 1 ! sd_dac $end
$var wire 5 " sd_count [4:0] $end
$var wire 1 # sclk_pre_fall $end
$var wire 1 $ sclk $end
$var wire 1 % rst_n_sync $end
$var wire 1 & lrclk $end
$var reg 24 ' left_data [23:0] $end
$var reg 1 ( locked $end
$var reg 1 ) mclk $end
$var reg 1 * resetn $end
$var reg 24 + right_data [23:0] $end
$scope module clock_test $end
$var wire 1 ( locked $end
$var wire 1 ) mclk $end
$var wire 1 * resetn $end
$var wire 1 , rst_n_async $end
$var wire 1 % rst_n_sync $end
$var wire 1 # sclk_pre_fall $end
$var wire 1 - sclk_pre_rise $end
$var wire 1 . sd_valid $end
$var wire 5 / sd_count [4:0] $end
$var reg 1 & lrclk $end
$var reg 2 0 mclk_count [1:0] $end
$var reg 1 1 rst_n_sync_1 $end
$var reg 1 2 rst_n_sync_2 $end
$var reg 1 $ sclk $end
$var reg 5 3 sclk_count [4:0] $end
$upscope $end
$scope module output_test $end
$var wire 24 4 left_data [23:0] $end
$var wire 1 & lrclk $end
$var wire 1 ) mclk $end
$var wire 24 5 right_data [23:0] $end
$var wire 1 % rst_n_sync $end
$var wire 1 # sclk_pre_fall $end
$var wire 5 6 sd_count [4:0] $end
$var reg 1 ! sd_dac $end
$upscope $end
$scope task receive_data $end
$var reg 1 7 channel $end
$var reg 24 8 data [23:0] $end
$upscope $end
$upscope $end
$enddefinitions $end
$comment Show the parameter values. $end
$dumpall
$end
#0
$dumpvars
bx 8
x7
b11111 6
bx 5
bx 4
b0 3
02
01
b0 0
b11111 /
0.
0-
0,
bx +
0*
0)
0(
bx '
x&
0%
x$
0#
b11111 "
x!
$end
#10000
0&
0$
0!
1)
#20000
0)
#30000
1)
#40000
0)
#50000
1)
1*
#60000
0)
#70000
11
1,
1)
1(
#80000
0)
#90000
1%
12
1)
#100000
0)
#110000
b1 0
1)
#120000
0)
#130000
b10 0
1)
#140000
0)
#150000
1-
b11 0
1)
#160000
0)
#170000
0-
b0 0
1$
1)
#180000
0)
#190000
b1 0
1)
#200000
0)
#210000
b10 0
1)
#220000
0)
#230000
1#
b11 0
1)
#240000
0)
#250000
1.
0#
b0 "
b0 /
b0 6
b1 3
b0 0
0$
x!
1)
#260000
0)
#270000
b1 0
1)
#280000
0)
#290000
b10 0
1)
#300000
0)
#310000
1-
b11 0
1)
#320000
0)
#330000
0-
b0 0
1$
1)
#340000
0)
#350000
b1 0
1)
#360000
0)
#370000
b10 0
1)
#380000
0)
#390000
1#
b11 0
1)
#400000
0)
#410000
0#
b1 "
b1 /
b1 6
b10 3
b0 0
0$
1)
#420000
0)
#430000
b1 0
1)
#440000
0)
#450000
b10 0
1)
#460000
0)
#470000
1-
b11 0
1)
#480000
0)
#490000
0-
b0 0
1$
1)
#500000
0)
#510000
b1 0
1)
#520000
0)
#530000
b10 0
1)
#540000
0)
#550000
1#
b11 0
1)
#560000
0)
#570000
0#
b10 "
b10 /
b10 6
b11 3
b0 0
0$
1)
#580000
0)
#590000
b1 0
1)
#600000
0)
#610000
b10 0
1)
#620000
0)
#630000
1-
b11 0
1)
#640000
0)
#650000
0-
b0 0
1$
1)
#660000
0)
#670000
b1 0
1)
#680000
0)
#690000
b10 0
1)
#700000
0)
#710000
1#
b11 0
1)
#720000
0)
#730000
0#
b11 "
b11 /
b11 6
b100 3
b0 0
0$
1)
#740000
0)
#750000
b1 0
1)
#760000
0)
#770000
b10 0
1)
#780000
0)
#790000
1-
b11 0
1)
#800000
0)
#810000
0-
b0 0
1$
1)
#820000
0)
#830000
b1 0
1)
#840000
0)
#850000
b10 0
1)
#860000
0)
#870000
1#
b11 0
1)
#880000
0)
#890000
0#
b100 "
b100 /
b100 6
b101 3
b0 0
0$
1)
#900000
0)
#910000
b1 0
1)
#920000
0)
#930000
b10 0
1)
#940000
0)
#950000
1-
b11 0
1)
#960000
0)
#970000
0-
b0 0
1$
1)
#980000
0)
#990000
b1 0
1)
#1000000
0)
#1010000
b10 0
1)
#1020000
0)
#1030000
1#
b11 0
1)
#1040000
0)
#1050000
0#
b101 "
b101 /
b101 6
b110 3
b0 0
0$
1)
#1060000
0)
#1070000
b1 0
1)
#1080000
0)
#1090000
b10 0
1)
#1100000
0)
#1110000
1-
b11 0
1)
#1120000
0)
#1130000
0-
b0 0
1$
1)
#1140000
0)
#1150000
b1 0
1)
#1160000
0)
#1170000
b10 0
1)
#1180000
0)
#1190000
1#
b11 0
1)
#1200000
0)
#1210000
0#
b110 "
b110 /
b110 6
b111 3
b0 0
0$
1)
#1220000
0)
#1230000
b1 0
1)
#1240000
0)
#1250000
b10 0
1)
#1260000
0)
#1270000
1-
b11 0
1)
#1280000
0)
#1290000
0-
b0 0
1$
1)
#1300000
0)
#1310000
b1 0
1)
#1320000
0)
#1330000
b10 0
1)
#1340000
0)
#1350000
1#
b11 0
1)
#1360000
0)
#1370000
0#
b111 "
b111 /
b111 6
b1000 3
b0 0
0$
1)
#1380000
0)
#1390000
b1 0
1)
#1400000
0)
#1410000
b10 0
1)
#1420000
0)
#1430000
1-
b11 0
1)
#1440000
0)
#1450000
0-
b0 0
1$
1)
#1460000
0)
#1470000
b1 0
1)
#1480000
0)
#1490000
b10 0
1)
#1500000
0)
#1510000
1#
b11 0
1)
#1520000
0)
#1530000
0#
b1000 "
b1000 /
b1000 6
b1001 3
b0 0
0$
1)
#1540000
0)
#1550000
b1 0
1)
#1560000
0)
#1570000
b10 0
1)
#1580000
0)
#1590000
1-
b11 0
1)
#1600000
0)
#1610000
0-
b0 0
1$
1)
#1620000
0)
#1630000
b1 0
1)
#1640000
0)
#1650000
b10 0
1)
#1660000
0)
#1670000
1#
b11 0
1)
#1680000
0)
#1690000
0#
b1001 "
b1001 /
b1001 6
b1010 3
b0 0
0$
1)
#1700000
0)
#1710000
b1 0
1)
#1720000
0)
#1730000
b10 0
1)
#1740000
0)
#1750000
1-
b11 0
1)
#1760000
0)
#1770000
0-
b0 0
1$
1)
#1780000
0)
#1790000
b1 0
1)
#1800000
0)
#1810000
b10 0
1)
#1820000
0)
#1830000
1#
b11 0
1)
#1840000
0)
#1850000
0#
b1010 "
b1010 /
b1010 6
b1011 3
b0 0
0$
1)
#1860000
0)
#1870000
b1 0
1)
#1880000
0)
#1890000
b10 0
1)
#1900000
0)
#1910000
1-
b11 0
1)
#1920000
0)
#1930000
0-
b0 0
1$
1)
#1940000
0)
#1950000
b1 0
1)
#1960000
0)
#1970000
b10 0
1)
#1980000
0)
#1990000
1#
b11 0
1)
#2000000
0)
#2010000
0#
b1011 "
b1011 /
b1011 6
b1100 3
b0 0
0$
1)
#2020000
0)
#2030000
b1 0
1)
#2040000
0)
#2050000
b10 0
1)
#2060000
0)
#2070000
1-
b11 0
1)
#2080000
0)
#2090000
0-
b0 0
1$
1)
#2100000
0)
#2110000
b1 0
1)
#2120000
0)
#2130000
b10 0
1)
#2140000
0)
#2150000
1#
b11 0
1)
#2160000
0)
#2170000
0#
b1100 "
b1100 /
b1100 6
b1101 3
b0 0
0$
1)
#2180000
0)
#2190000
b1 0
1)
#2200000
0)
#2210000
b10 0
1)
#2220000
0)
#2230000
1-
b11 0
1)
#2240000
0)
#2250000
0-
b0 0
1$
1)
#2260000
0)
#2270000
b1 0
1)
#2280000
0)
#2290000
b10 0
1)
#2300000
0)
#2310000
1#
b11 0
1)
#2320000
0)
#2330000
0#
b1101 "
b1101 /
b1101 6
b1110 3
b0 0
0$
1)
#2340000
0)
#2350000
b1 0
1)
#2360000
0)
#2370000
b10 0
1)
#2380000
0)
#2390000
1-
b11 0
1)
#2400000
0)
#2410000
0-
b0 0
1$
1)
#2420000
0)
#2430000
b1 0
1)
#2440000
0)
#2450000
b10 0
1)
#2460000
0)
#2470000
1#
b11 0
1)
#2480000
0)
#2490000
0#
b1110 "
b1110 /
b1110 6
b1111 3
b0 0
0$
1)
#2500000
0)
#2510000
b1 0
1)
#2520000
0)
#2530000
b10 0
1)
#2540000
0)
#2550000
1-
b11 0
1)
#2560000
0)
#2570000
0-
b0 0
1$
1)
#2580000
0)
#2590000
b1 0
1)
#2600000
0)
#2610000
b10 0
1)
#2620000
0)
#2630000
1#
b11 0
1)
#2640000
0)
#2650000
0#
b1111 "
b1111 /
b1111 6
b10000 3
b0 0
0$
1)
#2660000
0)
#2670000
b1 0
1)
#2680000
0)
#2690000
b10 0
1)
#2700000
0)
#2710000
1-
b11 0
1)
#2720000
0)
#2730000
0-
b0 0
1$
1)
#2740000
0)
#2750000
b1 0
1)
#2760000
0)
#2770000
b10 0
1)
#2780000
0)
#2790000
1#
b11 0
1)
#2800000
0)
#2810000
0#
b10000 "
b10000 /
b10000 6
b10001 3
b0 0
0$
1)
#2820000
0)
#2830000
b1 0
1)
#2840000
0)
#2850000
b10 0
1)
#2860000
0)
#2870000
1-
b11 0
1)
#2880000
0)
#2890000
0-
b0 0
1$
1)
#2900000
0)
#2910000
b1 0
1)
#2920000
0)
#2930000
b10 0
1)
#2940000
0)
#2950000
1#
b11 0
1)
#2960000
0)
#2970000
0#
b10001 "
b10001 /
b10001 6
b10010 3
b0 0
0$
1)
#2980000
0)
#2990000
b1 0
1)
#3000000
0)
#3010000
b10 0
1)
#3020000
0)
#3030000
1-
b11 0
1)
#3040000
0)
#3050000
0-
b0 0
1$
1)
#3060000
0)
#3070000
b1 0
1)
#3080000
0)
#3090000
b10 0
1)
#3100000
0)
#3110000
1#
b11 0
1)
#3120000
0)
#3130000
0#
b10010 "
b10010 /
b10010 6
b10011 3
b0 0
0$
1)
#3140000
0)
#3150000
b1 0
1)
#3160000
0)
#3170000
b10 0
1)
#3180000
0)
#3190000
1-
b11 0
1)
#3200000
0)
#3210000
0-
b0 0
1$
1)
#3220000
0)
#3230000
b1 0
1)
#3240000
0)
#3250000
b10 0
1)
#3260000
0)
#3270000
1#
b11 0
1)
#3280000
0)
#3290000
0#
b10011 "
b10011 /
b10011 6
b10100 3
b0 0
0$
1)
#3300000
0)
#3310000
b1 0
1)
#3320000
0)
#3330000
b10 0
1)
#3340000
0)
#3350000
1-
b11 0
1)
#3360000
0)
#3370000
0-
b0 0
1$
1)
#3380000
0)
#3390000
b1 0
1)
#3400000
0)
#3410000
b10 0
1)
#3420000
0)
#3430000
1#
b11 0
1)
#3440000
0)
#3450000
0#
b10100 "
b10100 /
b10100 6
b10101 3
b0 0
0$
1)
#3460000
0)
#3470000
b1 0
1)
#3480000
0)
#3490000
b10 0
1)
#3500000
0)
#3510000
1-
b11 0
1)
#3520000
0)
#3530000
0-
b0 0
1$
1)
#3540000
0)
#3550000
b1 0
1)
#3560000
0)
#3570000
b10 0
1)
#3580000
0)
#3590000
1#
b11 0
1)
#3600000
0)
#3610000
0#
b10101 "
b10101 /
b10101 6
b10110 3
b0 0
0$
1)
#3620000
0)
#3630000
b1 0
1)
#3640000
0)
#3650000
b10 0
1)
#3660000
0)
#3670000
1-
b11 0
1)
#3680000
0)
#3690000
0-
b0 0
1$
1)
#3700000
0)
#3710000
b1 0
1)
#3720000
0)
#3730000
b10 0
1)
#3740000
0)
#3750000
1#
b11 0
1)
#3760000
0)
#3770000
0#
b10110 "
b10110 /
b10110 6
b10111 3
b0 0
0$
1)
#3780000
0)
#3790000
b1 0
1)
#3800000
0)
#3810000
b10 0
1)
#3820000
0)
#3830000
1-
b11 0
1)
#3840000
0)
#3850000
0-
b0 0
1$
1)
#3860000
0)
#3870000
b1 0
1)
#3880000
0)
#3890000
b10 0
1)
#3900000
0)
#3910000
1#
b11 0
1)
#3920000
0)
#3930000
0#
b10111 "
b10111 /
b10111 6
b11000 3
b0 0
0$
1)
#3940000
0)
#3950000
b1 0
1)
#3960000
0)
#3970000
b10 0
1)
#3980000
0)
#3990000
1-
b11 0
1)
#4000000
0)
#4010000
0-
b0 0
1$
1)
#4020000
0)
#4030000
b1 0
1)
#4040000
0)
#4050000
b10 0
1)
#4060000
0)
#4070000
1#
b11 0
1)
#4080000
0)
#4090000
0.
0#
b11000 "
b11000 /
b11000 6
b11001 3
b0 0
0$
0!
1)
#4100000
0)
#4110000
b1 0
1)
#4120000
0)
#4130000
b10 0
1)
#4140000
0)
#4150000
1-
b11 0
1)
#4160000
0)
#4170000
0-
b0 0
1$
1)
#4180000
0)
#4190000
b1 0
1)
#4200000
0)
#4210000
b10 0
1)
#4220000
0)
#4230000
1#
b11 0
1)
#4240000
0)
#4250000
0#
b11001 "
b11001 /
b11001 6
b11010 3
b0 0
0$
1)
#4260000
0)
#4270000
b1 0
1)
#4280000
0)
#4290000
b10 0
1)
#4300000
0)
#4310000
1-
b11 0
1)
#4320000
0)
#4330000
0-
b0 0
1$
1)
#4340000
0)
#4350000
b1 0
1)
#4360000
0)
#4370000
b10 0
1)
#4380000
0)
#4390000
1#
b11 0
1)
#4400000
0)
#4410000
0#
b11010 "
b11010 /
b11010 6
b11011 3
b0 0
0$
1)
#4420000
0)
#4430000
b1 0
1)
#4440000
0)
#4450000
b10 0
1)
#4460000
0)
#4470000
1-
b11 0
1)
#4480000
0)
#4490000
0-
b0 0
1$
1)
#4500000
0)
#4510000
b1 0
1)
#4520000
0)
#4530000
b10 0
1)
#4540000
0)
#4550000
1#
b11 0
1)
#4560000
0)
#4570000
0#
b11011 "
b11011 /
b11011 6
b11100 3
b0 0
0$
1)
#4580000
0)
#4590000
b1 0
1)
#4600000
0)
#4610000
b10 0
1)
#4620000
0)
#4630000
1-
b11 0
1)
#4640000
0)
#4650000
0-
b0 0
1$
1)
#4660000
0)
#4670000
b1 0
1)
#4680000
0)
#4690000
b10 0
1)
#4700000
0)
#4710000
1#
b11 0
1)
#4720000
0)
#4730000
0#
b11100 "
b11100 /
b11100 6
b11101 3
b0 0
0$
1)
#4740000
0)
#4750000
b1 0
1)
#4760000
0)
#4770000
b10 0
1)
#4780000
0)
#4790000
1-
b11 0
1)
#4800000
0)
#4810000
0-
b0 0
1$
1)
#4820000
0)
#4830000
b1 0
1)
#4840000
0)
#4850000
b10 0
1)
#4860000
0)
#4870000
1#
b11 0
1)
#4880000
0)
#4890000
0#
b11101 "
b11101 /
b11101 6
b11110 3
b0 0
0$
1)
#4900000
0)
#4910000
b1 0
1)
#4920000
0)
#4930000
b10 0
1)
#4940000
0)
#4950000
1-
b11 0
1)
#4960000
0)
#4970000
0-
b0 0
1$
1)
#4980000
0)
#4990000
b1 0
1)
#5000000
0)
#5010000
b10 0
1)
#5020000
0)
#5030000
1#
b11 0
1)
#5040000
0)
#5050000
0#
b11110 "
b11110 /
b11110 6
b11111 3
b0 0
0$
1)
#5060000
0)
#5070000
b1 0
1)
#5080000
0)
#5090000
b10 0
1)
#5100000
0)
#5110000
1-
b11 0
1)
#5120000
0)
#5130000
0-
b0 0
1$
1)
#5140000
0)
#5150000
b1 0
1)
#5160000
0)
#5170000
b10 0
1)
#5180000
0)
#5190000
1#
b11 0
1)
#5200000
0)
#5210000
17
b110110101101101110101101 8
0#
b11111 "
b11111 /
b11111 6
b0 3
1&
b0 0
0$
1)
#5220000
0)
#5230000
b1 0
1)
#5240000
0)
#5250000
b10 0
1)
#5260000
0)
#5270000
1-
b11 0
1)
#5280000
0)
#5290000
0-
b0 0
1$
1)
#5300000
0)
#5310000
b1 0
1)
#5320000
0)
#5330000
b10 0
1)
#5340000
0)
#5350000
1#
b11 0
1)
#5360000
0)
#5370000
1.
0#
b0 "
b0 /
b0 6
b1 3
b0 0
0$
x!
1)
#5380000
0)
#5390000
b1 0
1)
#5400000
0)
#5410000
b10 0
1)
#5420000
0)
#5430000
1-
b11 0
1)
#5440000
0)
#5450000
0-
b0 0
1$
1)
#5460000
0)
#5470000
b1 0
1)
#5480000
0)
#5490000
b10 0
1)
#5500000
0)
#5510000
1#
b11 0
1)
#5520000
0)
#5530000
0#
b1 "
b1 /
b1 6
b10 3
b0 0
0$
1)
#5540000
0)
#5550000
b1 0
1)
#5560000
0)
#5570000
b10 0
1)
#5580000
0)
#5590000
1-
b11 0
1)
#5600000
0)
#5610000
0-
b0 0
1$
1)
#5620000
0)
#5630000
b1 0
1)
#5640000
0)
#5650000
b10 0
1)
#5660000
0)
#5670000
1#
b11 0
1)
#5680000
0)
#5690000
0#
b10 "
b10 /
b10 6
b11 3
b0 0
0$
1)
#5700000
0)
#5710000
b1 0
1)
#5720000
0)
#5730000
b10 0
1)
#5740000
0)
#5750000
1-
b11 0
1)
#5760000
0)
#5770000
0-
b0 0
1$
1)
#5780000
0)
#5790000
b1 0
1)
#5800000
0)
#5810000
b10 0
1)
#5820000
0)
#5830000
1#
b11 0
1)
#5840000
0)
#5850000
0#
b11 "
b11 /
b11 6
b100 3
b0 0
0$
1)
#5860000
0)
#5870000
b1 0
1)
#5880000
0)
#5890000
b10 0
1)
#5900000
0)
#5910000
1-
b11 0
1)
#5920000
0)
#5930000
0-
b0 0
1$
1)
#5940000
0)
#5950000
b1 0
1)
#5960000
0)
#5970000
b10 0
1)
#5980000
0)
#5990000
1#
b11 0
1)
#6000000
0)
#6010000
0#
b100 "
b100 /
b100 6
b101 3
b0 0
0$
1)
#6020000
0)
#6030000
b1 0
1)
#6040000
0)
#6050000
b10 0
1)
#6060000
0)
#6070000
1-
b11 0
1)
#6080000
0)
#6090000
0-
b0 0
1$
1)
#6100000
0)
#6110000
b1 0
1)
#6120000
0)
#6130000
b10 0
1)
#6140000
0)
#6150000
1#
b11 0
1)
#6160000
0)
#6170000
0#
b101 "
b101 /
b101 6
b110 3
b0 0
0$
1)
#6180000
0)
#6190000
b1 0
1)
#6200000
0)
#6210000
b10 0
1)
#6220000
0)
#6230000
1-
b11 0
1)
#6240000
0)
#6250000
0-
b0 0
1$
1)
#6260000
0)
#6270000
b1 0
1)
#6280000
0)
#6290000
b10 0
1)
#6300000
0)
#6310000
1#
b11 0
1)
#6320000
0)
#6330000
0#
b110 "
b110 /
b110 6
b111 3
b0 0
0$
1)
#6340000
0)
#6350000
b1 0
1)
#6360000
0)
#6370000
b10 0
1)
#6380000
0)
#6390000
1-
b11 0
1)
#6400000
0)
#6410000
0-
b0 0
1$
1)
#6420000
0)
#6430000
b1 0
1)
#6440000
0)
#6450000
b10 0
1)
#6460000
0)
#6470000
1#
b11 0
1)
#6480000
0)
#6490000
0#
b111 "
b111 /
b111 6
b1000 3
b0 0
0$
1)
#6500000
0)
#6510000
b1 0
1)
#6520000
0)
#6530000
b10 0
1)
#6540000
0)
#6550000
1-
b11 0
1)
#6560000
0)
#6570000
0-
b0 0
1$
1)
#6580000
0)
#6590000
b1 0
1)
#6600000
0)
#6610000
b10 0
1)
#6620000
0)
#6630000
1#
b11 0
1)
#6640000
0)
#6650000
0#
b1000 "
b1000 /
b1000 6
b1001 3
b0 0
0$
1)
#6660000
0)
#6670000
b1 0
1)
#6680000
0)
#6690000
b10 0
1)
#6700000
0)
#6710000
1-
b11 0
1)
#6720000
0)
#6730000
0-
b0 0
1$
1)
#6740000
0)
#6750000
b1 0
1)
#6760000
0)
#6770000
b10 0
1)
#6780000
0)
#6790000
1#
b11 0
1)
#6800000
0)
#6810000
0#
b1001 "
b1001 /
b1001 6
b1010 3
b0 0
0$
1)
#6820000
0)
#6830000
b1 0
1)
#6840000
0)
#6850000
b10 0
1)
#6860000
0)
#6870000
1-
b11 0
1)
#6880000
0)
#6890000
0-
b0 0
1$
1)
#6900000
0)
#6910000
b1 0
1)
#6920000
0)
#6930000
b10 0
1)
#6940000
0)
#6950000
1#
b11 0
1)
#6960000
0)
#6970000
0#
b1010 "
b1010 /
b1010 6
b1011 3
b0 0
0$
1)
#6980000
0)
#6990000
b1 0
1)
#7000000
0)
#7010000
b10 0
1)
#7020000
0)
#7030000
1-
b11 0
1)
#7040000
0)
#7050000
0-
b0 0
1$
1)
#7060000
0)
#7070000
b1 0
1)
#7080000
0)
#7090000
b10 0
1)
#7100000
0)
#7110000
1#
b11 0
1)
#7120000
0)
#7130000
0#
b1011 "
b1011 /
b1011 6
b1100 3
b0 0
0$
1)
#7140000
0)
#7150000
b1 0
1)
#7160000
0)
#7170000
b10 0
1)
#7180000
0)
#7190000
1-
b11 0
1)
#7200000
0)
#7210000
0-
b0 0
1$
1)
#7220000
0)
#7230000
b1 0
1)
#7240000
0)
#7250000
b10 0
1)
#7260000
0)
#7270000
1#
b11 0
1)
#7280000
0)
#7290000
0#
b1100 "
b1100 /
b1100 6
b1101 3
b0 0
0$
1)
#7300000
0)
#7310000
b1 0
1)
#7320000
0)
#7330000
b10 0
1)
#7340000
0)
#7350000
1-
b11 0
1)
#7360000
0)
#7370000
0-
b0 0
1$
1)
#7380000
0)
#7390000
b1 0
1)
#7400000
0)
#7410000
b10 0
1)
#7420000
0)
#7430000
1#
b11 0
1)
#7440000
0)
#7450000
0#
b1101 "
b1101 /
b1101 6
b1110 3
b0 0
0$
1)
#7460000
0)
#7470000
b1 0
1)
#7480000
0)
#7490000
b10 0
1)
#7500000
0)
#7510000
1-
b11 0
1)
#7520000
0)
#7530000
0-
b0 0
1$
1)
#7540000
0)
#7550000
b1 0
1)
#7560000
0)
#7570000
b10 0
1)
#7580000
0)
#7590000
1#
b11 0
1)
#7600000
0)
#7610000
0#
b1110 "
b1110 /
b1110 6
b1111 3
b0 0
0$
1)
#7620000
0)
#7630000
b1 0
1)
#7640000
0)
#7650000
b10 0
1)
#7660000
0)
#7670000
1-
b11 0
1)
#7680000
0)
#7690000
0-
b0 0
1$
1)
#7700000
0)
#7710000
b1 0
1)
#7720000
0)
#7730000
b10 0
1)
#7740000
0)
#7750000
1#
b11 0
1)
#7760000
0)
#7770000
0#
b1111 "
b1111 /
b1111 6
b10000 3
b0 0
0$
1)
#7780000
0)
#7790000
b1 0
1)
#7800000
0)
#7810000
b10 0
1)
#7820000
0)
#7830000
1-
b11 0
1)
#7840000
0)
#7850000
0-
b0 0
1$
1)
#7860000
0)
#7870000
b1 0
1)
#7880000
0)
#7890000
b10 0
1)
#7900000
0)
#7910000
1#
b11 0
1)
#7920000
0)
#7930000
0#
b10000 "
b10000 /
b10000 6
b10001 3
b0 0
0$
1)
#7940000
0)
#7950000
b1 0
1)
#7960000
0)
#7970000
b10 0
1)
#7980000
0)
#7990000
1-
b11 0
1)
#8000000
0)
#8010000
0-
b0 0
1$
1)
#8020000
0)
#8030000
b1 0
1)
#8040000
0)
#8050000
b10 0
1)
#8060000
0)
#8070000
1#
b11 0
1)
#8080000
0)
#8090000
0#
b10001 "
b10001 /
b10001 6
b10010 3
b0 0
0$
1)
#8100000
0)
#8110000
b1 0
1)
#8120000
0)
#8130000
b10 0
1)
#8140000
0)
#8150000
1-
b11 0
1)
#8160000
0)
#8170000
0-
b0 0
1$
1)
#8180000
0)
#8190000
b1 0
1)
#8200000
0)
#8210000
b10 0
1)
#8220000
0)
#8230000
1#
b11 0
1)
#8240000
0)
#8250000
0#
b10010 "
b10010 /
b10010 6
b10011 3
b0 0
0$
1)
#8260000
0)
#8270000
b1 0
1)
#8280000
0)
#8290000
b10 0
1)
#8300000
0)
#8310000
1-
b11 0
1)
#8320000
0)
#8330000
0-
b0 0
1$
1)
#8340000
0)
#8350000
b1 0
1)
#8360000
0)
#8370000
b10 0
1)
#8380000
0)
#8390000
1#
b11 0
1)
#8400000
0)
#8410000
0#
b10011 "
b10011 /
b10011 6
b10100 3
b0 0
0$
1)
#8420000
0)
#8430000
b1 0
1)
#8440000
0)
#8450000
b10 0
1)
#8460000
0)
#8470000
1-
b11 0
1)
#8480000
0)
#8490000
0-
b0 0
1$
1)
#8500000
0)
#8510000
b1 0
1)
#8520000
0)
#8530000
b10 0
1)
#8540000
0)
#8550000
1#
b11 0
1)
#8560000
0)
#8570000
0#
b10100 "
b10100 /
b10100 6
b10101 3
b0 0
0$
1)
#8580000
0)
#8590000
b1 0
1)
#8600000
0)
#8610000
b10 0
1)
#8620000
0)
#8630000
1-
b11 0
1)
#8640000
0)
#8650000
0-
b0 0
1$
1)
#8660000
0)
#8670000
b1 0
1)
#8680000
0)
#8690000
b10 0
1)
#8700000
0)
#8710000
1#
b11 0
1)
#8720000
0)
#8730000
0#
b10101 "
b10101 /
b10101 6
b10110 3
b0 0
0$
1)
#8740000
0)
#8750000
b1 0
1)
#8760000
0)
#8770000
b10 0
1)
#8780000
0)
#8790000
1-
b11 0
1)
#8800000
0)
#8810000
0-
b0 0
1$
1)
#8820000
0)
#8830000
b1 0
1)
#8840000
0)
#8850000
b10 0
1)
#8860000
0)
#8870000
1#
b11 0
1)
#8880000
0)
#8890000
0#
b10110 "
b10110 /
b10110 6
b10111 3
b0 0
0$
1)
#8900000
0)
